vulnq/__init__.py
vulnq/cli.py
vulnq/core.py
vulnq/models.py
vulnq/utils.py
vulnq/clients/__init__.py
vulnq/clients/base.py
vulnq/clients/github.py
vulnq/clients/nvd.py
vulnq/clients/osv.py
vulnq/clients/vulnerablecode.py
vulnq-1.0.2.dist-info/licenses/AUTHORS.md
vulnq-1.0.2.dist-info/licenses/LICENSE
vulnq-1.0.2.dist-info/METADATA
vulnq-1.0.2.dist-info/WHEEL
vulnq-1.0.2.dist-info/entry_points.txt
vulnq-1.0.2.dist-info/top_level.txt
vulnq-1.0.2.dist-info/RECORD
