Metadata-Version: 2.4
Name: vulnq
Version: 1.0.2
Summary: Lightweight vulnerability query tool for multi-source security data aggregation
Author-email: "Oscar Valenzuela B." <oscar.valenzuela.b@gmail.com>
Maintainer-email: "Oscar Valenzuela B." <oscar.valenzuela.b@gmail.com>
License: Apache-2.0
Project-URL: Homepage, https://github.com/SemClone/vulnq
Project-URL: Documentation, https://github.com/SemClone/vulnq/blob/main/README.md
Project-URL: Repository, https://github.com/SemClone/vulnq.git
Project-URL: Issues, https://github.com/SemClone/vulnq/issues
Project-URL: Changelog, https://github.com/SemClone/vulnq/blob/main/CHANGELOG.md
Keywords: vulnerability,security,cve,osv,nvd,purl,cpe,vulnerability-scanner,vulnerability-database,sbom,sca,supply-chain
Classifier: Development Status :: 5 - Production/Stable
Classifier: Intended Audience :: Developers
Classifier: Intended Audience :: Information Technology
Classifier: Intended Audience :: System Administrators
Classifier: Topic :: Security
Classifier: Topic :: Software Development :: Libraries :: Python Modules
Classifier: Topic :: Software Development :: Quality Assurance
Classifier: Topic :: System :: Software Distribution
Classifier: Programming Language :: Python :: 3
Classifier: Programming Language :: Python :: 3.8
Classifier: Programming Language :: Python :: 3.9
Classifier: Programming Language :: Python :: 3.10
Classifier: Programming Language :: Python :: 3.11
Classifier: Programming Language :: Python :: 3.12
Classifier: Programming Language :: Python :: 3.13
Classifier: Operating System :: OS Independent
Classifier: License :: OSI Approved :: Apache Software License
Requires-Python: >=3.8
License-File: LICENSE
License-File: AUTHORS.md
Requires-Dist: click>=8.0.0
Requires-Dist: requests>=2.28.0
Requires-Dist: aiohttp>=3.8.0
Requires-Dist: pydantic>=2.0.0
Requires-Dist: packageurl-python>=0.11.0
Requires-Dist: rich>=13.0.0
Requires-Dist: python-dateutil>=2.8.0
Requires-Dist: pyyaml>=6.0
Requires-Dist: jsonschema>=4.17.0
Provides-Extra: dev
Requires-Dist: pytest>=7.0.0; extra == "dev"
Requires-Dist: pytest-cov>=4.0.0; extra == "dev"
Requires-Dist: pytest-asyncio>=0.21.0; extra == "dev"
Requires-Dist: black>=23.0.0; extra == "dev"
Requires-Dist: isort>=5.11.0; extra == "dev"
Requires-Dist: flake8>=6.0.0; extra == "dev"
Requires-Dist: mypy>=1.0.0; extra == "dev"
Requires-Dist: pre-commit>=3.0.0; extra == "dev"
Provides-Extra: cache
Requires-Dist: diskcache>=5.0.0; extra == "cache"
Provides-Extra: all
Requires-Dist: vulnq[cache,dev]; extra == "all"
Dynamic: license-file
